{"cameraMode":{"drawMode":0,"name":"Shaded","section":"Shading Mode"},"sceneLighting":true,"audioPlay":false,"sceneViewState":{"m_AlwaysRefresh":false,"showFog":true,"showSkybox":true,"showFlares":true,"showImageEffects":true,"showParticleSystems":true,"showVisualEffectGraphs":true,"m_FxEnabled":true},"in2DMode":false,"pivot":{"x":2.047398805618286,"y":1.4078454971313477,"z":15.755813598632813},"rotation":{"x":-0.08113497495651245,"y":-0.04573453217744827,"z":0.0037256604991853239,"w":-0.9956501722335815},"size":9.12105655670166,"orthographic":false}